[
    {
        "Date": "2023-03-15T00:00:00",
        "Open": 149.68050801163758,
        "High": 151.71993837140982,
        "Low": 148.42318357477492,
        "Close": 151.46253967285156,
        "Volume": 77167900,
        "ShortEMA": 149.3566600938183,
        "LongEMA": 147.33114500267334,
        "TrendFilterMA": 143.23381057739257,
        "SignalUnfiltered": "hold",
        "SignalFiltered": "hold"
    },
    {
        "Date": "2023-03-16T00:00:00",
        "Open": 150.64082983435895,
        "High": 154.89790141964556,
        "Low": 150.1260173130943,
        "Close": 154.2939910888672,
        "Volume": 76161100,
        "ShortEMA": 150.11624947767197,
        "LongEMA": 147.84691137942843,
        "TrendFilterMA": 143.84703994750976,
        "SignalUnfiltered": "hold",
        "SignalFiltered": "hold"
    },
    {
        "Date": "2023-03-17T00:00:00",
        "Open": 154.52170325241562,
        "High": 155.17511745555205,
        "Low": 152.7396713831552,
        "Close": 153.45248413085938,
        "Volume": 98944600,
        "ShortEMA": 150.62951634739312,
        "LongEMA": 148.26213899064555,
        "TrendFilterMA": 144.41793563842774,
        "SignalUnfiltered": "hold",
        "SignalFiltered": "hold"
    },
    {
        "Date": "2023-03-20T00:00:00",
        "Open": 153.52179760346752,
        "High": 156.24434176719376,
        "Low": 152.61096953502098,
        "Close": 155.82852172851562,
        "Volume": 73641400,
        "ShortEMA": 151.42936332910426,
        "LongEMA": 148.82261178604332,
        "TrendFilterMA": 145.06284393310546,
        "SignalUnfiltered": "hold",
        "SignalFiltered": "hold"
    },
    {
        "Date": "2023-03-21T00:00:00",
        "Open": 155.74930512262205,
        "High": 157.80852485445894,
        "Low": 154.9770788401289,
        "Close": 157.68972778320312,
        "Volume": 73938300,
        "ShortEMA": 152.39249632204255,
        "LongEMA": 149.47943519324033,
        "TrendFilterMA": 145.65403411865233,
        "SignalUnfiltered": "hold",
        "SignalFiltered": "hold"
    },
    {
        "Date": "2023-03-22T00:00:00",
        "Open": 157.70955140928402,
        "High": 160.5211932163919,
        "Low": 156.23442213481738,
        "Close": 156.2542266845703,
        "Volume": 75701800,
        "ShortEMA": 152.98660868550834,
        "LongEMA": 149.98127160000553,
        "TrendFilterMA": 146.20603576660156,
        "SignalUnfiltered": "hold",
        "SignalFiltered": "hold"
    },
    {
        "Date": "2023-03-23T00:00:00",
        "Open": 157.24423866782476,
        "High": 159.9370833205621,
        "Low": 156.10571123599644,
        "Close": 157.34323120117188,
        "Volume": 67622100,
        "ShortEMA": 153.65685830330273,
        "LongEMA": 150.52660194083268,
        "TrendFilterMA": 146.76835083007813,
        "SignalUnfiltered": "hold",
        "SignalFiltered": "hold"
    },
    {
        "Date": "2023-03-24T00:00:00",
        "Open": 157.27391824812167,
        "High": 158.73913747364256,
        "Low": 156.2740076797667,
        "Close": 158.65003967285156,
        "Volume": 59196500,
        "ShortEMA": 154.42504005246408,
        "LongEMA": 151.12833806913036,
        "TrendFilterMA": 147.302236328125,
        "SignalUnfiltered": "hold",
        "SignalFiltered": "hold"
    },
    {
        "Date": "2023-03-27T00:00:00",
        "Open": 158.34315238139064,
        "High": 159.1648674270664,
        "Low": 156.29381212775743,
        "Close": 156.69972229003906,
        "Volume": 52390300,
        "ShortEMA": 154.77499116593717,
        "LongEMA": 151.54103319660507,
        "TrendFilterMA": 147.79869689941407,
        "SignalUnfiltered": "hold",
        "SignalFiltered": "hold"
    },
    {
        "Date": "2023-03-28T00:00:00",
        "Open": 156.39283166414998,
        "High": 156.90764422361815,
        "Low": 154.4226943488484,
        "Close": 156.07601928710938,
        "Volume": 45992200,
        "ShortEMA": 154.9751493384252,
        "LongEMA": 151.87695809219798,
        "TrendFilterMA": 148.25599395751954,
        "SignalUnfiltered": "hold",
        "SignalFiltered": "hold"
    },
    {
        "Date": "2023-03-29T00:00:00",
        "Open": 157.77883979840226,
        "High": 159.44207447801494,
        "Low": 157.75905035570605,
        "Close": 159.1648712158203,
        "Volume": 51305700,
        "ShortEMA": 155.61972193494753,
        "LongEMA": 152.4168035087626,
        "TrendFilterMA": 148.75173919677735,
        "SignalUnfiltered": "hold",
        "SignalFiltered": "hold"
    },
    {
        "Date": "2023-03-30T00:00:00",
        "Open": 159.9172681392784,
        "High": 160.8478855082498,
        "Low": 159.65986944195512,
        "Close": 160.73898315429688,
        "Volume": 49501700,
        "ShortEMA": 156.4073005840782,
        "LongEMA": 153.03326126028367,
        "TrendFilterMA": 149.29339935302735,
        "SignalUnfiltered": "hold",
        "SignalFiltered": "hold"
    },
    {
        "Date": "2023-03-31T00:00:00",
        "Open": 160.8182007028279,
        "High": 163.35263923391068,
        "Low": 160.29349343380431,
        "Close": 163.25363159179688,
        "Volume": 68749800,
        "ShortEMA": 157.4605822775734,
        "LongEMA": 153.79032572928463,
        "TrendFilterMA": 149.88416564941406,
        "SignalUnfiltered": "hold",
        "SignalFiltered": "hold"
    },
    {
        "Date": "2023-04-03T00:00:00",
        "Open": 162.62993146566447,
        "High": 164.62975289569243,
        "Low": 162.58042764470542,
        "Close": 164.51095581054688,
        "Volume": 56976200,
        "ShortEMA": 158.54525512880008,
        "LongEMA": 154.5844464760448,
        "TrendFilterMA": 150.44867645263673,
        "SignalUnfiltered": "hold",
        "SignalFiltered": "hold"
    },
    {
        "Date": "2023-04-04T00:00:00",
        "Open": 164.9366655701128,
        "High": 165.17425973324032,
        "Low": 163.46153634610226,
        "Close": 163.97634887695312,
        "Volume": 46278300,
        "ShortEMA": 159.38080801313131,
        "LongEMA": 155.28014295018616,
        "TrendFilterMA": 150.93843963623047,
        "SignalUnfiltered": "hold",
        "SignalFiltered": "hold"
    },
    {
        "Date": "2023-04-05T00:00:00",
        "Open": 163.09525716874828,
        "High": 163.40215974161865,
        "Low": 160.1846074281314,
        "Close": 162.12503051757812,
        "Volume": 51511700,
        "ShortEMA": 159.8029960907385,
        "LongEMA": 155.78717165888187,
        "TrendFilterMA": 151.36310302734375,
        "SignalUnfiltered": "hold",
        "SignalFiltered": "hold"
    },
    {
        "Date": "2023-04-06T00:00:00",
        "Open": 160.80827539475462,
        "High": 163.31302951982073,
        "Low": 160.3825758088242,
        "Close": 163.01602172851562,
        "Volume": 45390100,
        "ShortEMA": 160.2973077273196,
        "LongEMA": 156.3226420344103,
        "TrendFilterMA": 151.8188317871094,
        "SignalUnfiltered": "hold",
        "SignalFiltered": "hold"
    },
    {
        "Date": "2023-04-10T00:00:00",
        "Open": 159.80836691031573,
        "High": 160.4122772216797,
        "Low": 158.48174921205518,
        "Close": 160.4122772216797,
        "Volume": 47716900,
        "ShortEMA": 160.31499534183655,
        "LongEMA": 156.62557797420803,
        "TrendFilterMA": 152.1809686279297,
        "SignalUnfiltered": "hold",
        "SignalFiltered": "hold"
    },
    {
        "Date": "2023-04-11T00:00:00",
        "Open": 160.72912334632053,
        "High": 160.73901806921322,
        "Low": 158.90748220210756,
        "Close": 159.19459533691406,
        "Volume": 47644200,
        "ShortEMA": 160.14262611031,
        "LongEMA": 156.8158755566307,
        "TrendFilterMA": 152.47980529785156,
        "SignalUnfiltered": "hold",
        "SignalFiltered": "hold"
    },
    {
        "Date": "2023-04-12T00:00:00",
        "Open": 159.61038476928212,
        "High": 160.44199460478865,
        "Low": 158.18475927615913,
        "Close": 158.50157165527344,
        "Volume": 50133100,
        "ShortEMA": 159.89015619415053,
        "LongEMA": 156.94074193430794,
        "TrendFilterMA": 152.82270782470704,
        "SignalUnfiltered": "hold",
        "SignalFiltered": "hold"
    },
    {
        "Date": "2023-04-13T00:00:00",
        "Open": 160.01627300479524,
        "High": 164.1446374499689,
        "Low": 159.8083630212289,
        "Close": 163.9070281982422,
        "Volume": 68445600,
        "ShortEMA": 160.50813650247233,
        "LongEMA": 157.4567631390438,
        "TrendFilterMA": 153.2482162475586,
        "SignalUnfiltered": "hold",
        "SignalFiltered": "hold"
    },
    {
        "Date": "2023-04-14T00:00:00",
        "Open": 162.94672669437054,
        "High": 164.65946521821587,
        "Low": 162.18442526560762,
        "Close": 163.560546875,
        "Volume": 49386500,
        "ShortEMA": 160.97773809824582,
        "LongEMA": 157.90889526763314,
        "TrendFilterMA": 153.64425689697265,
        "SignalUnfiltered": "hold",
        "SignalFiltered": "hold"
    },
    {
        "Date": "2023-04-17T00:00:00",
        "Open": 163.4417206444433,
        "High": 163.73872843453088,
        "Low": 162.39230621171848,
        "Close": 163.580322265625,
        "Volume": 41516200,
        "ShortEMA": 161.378135662458,
        "LongEMA": 158.3290009711881,
        "TrendFilterMA": 153.93413208007811,
        "SignalUnfiltered": "hold",
        "SignalFiltered": "hold"
    },
    {
        "Date": "2023-04-18T00:00:00",
        "Open": 164.44168227100437,
        "High": 165.7386009608918,
        "Low": 163.9961629353784,
        "Close": 164.8079833984375,
        "Volume": 49923000,
        "ShortEMA": 161.90580454491638,
        "LongEMA": 158.8089255954288,
        "TrendFilterMA": 154.17580627441407,
        "SignalUnfiltered": "hold",
        "SignalFiltered": "hold"
    },
    {
        "Date": "2023-04-19T00:00:00",
        "Open": 164.14465925023921,
        "High": 166.48109766330478,
        "Low": 163.8872454167369,
        "Close": 165.95639038085938,
        "Volume": 47720200,
        "ShortEMA": 162.52897159659992,
        "LongEMA": 159.33836743138662,
        "TrendFilterMA": 154.49521179199218,
        "SignalUnfiltered": "hold",
        "SignalFiltered": "hold"
    },
    {
        "Date": "2023-04-20T00:00:00",
        "Open": 164.43175373561738,
        "High": 166.19398100625685,
        "Low": 163.90704646438456,
        "Close": 164.9861602783203,
        "Volume": 52456400,
        "ShortEMA": 162.9070006245569,
        "LongEMA": 159.7567224570854,
        "TrendFilterMA": 154.7374838256836,
        "SignalUnfiltered": "hold",
        "SignalFiltered": "hold"
    },
    {
        "Date": "2023-04-21T00:00:00",
        "Open": 163.40212053189984,
        "High": 164.7881366917755,
        "Low": 162.84771406794957,
        "Close": 163.37242126464844,
        "Volume": 58337300,
        "ShortEMA": 162.9786037999556,
        "LongEMA": 160.02455199838636,
        "TrendFilterMA": 155.0014535522461,
        "SignalUnfiltered": "hold",
        "SignalFiltered": "hold"
    },
    {
        "Date": "2023-04-24T00:00:00",
        "Open": 163.3526447044582,
        "High": 163.94666036414364,
        "Low": 162.25372630855222,
        "Close": 163.67935180664062,
        "Volume": 41949600,
        "ShortEMA": 163.08641118559945,
        "LongEMA": 160.2952779101089,
        "TrendFilterMA": 155.29232055664062,
        "SignalUnfiltered": "hold",
        "SignalFiltered": "hold"
    },
    {
        "Date": "2023-04-25T00:00:00",
        "Open": 163.54075445626503,
        "High": 164.64956760321772,
        "Low": 162.09532436989073,
        "Close": 162.1349334716797,
        "Volume": 48714100,
        "ShortEMA": 162.94002999884256,
        "LongEMA": 160.43154869244748,
        "TrendFilterMA": 155.54497314453124,
        "SignalUnfiltered": "hold",
        "SignalFiltered": "hold"
    },
    {
        "Date": "2023-04-26T00:00:00",
        "Open": 161.43202227134714,
        "High": 163.6298592139988,
        "Low": 161.174623524589,
        "Close": 162.12503051757812,
        "Volume": 45498800,
        "ShortEMA": 162.81464546326342,
        "LongEMA": 160.5569917906053,
        "TrendFilterMA": 155.7411944580078,
        "SignalUnfiltered": "hold",
        "SignalFiltered": "hold"
    },
    {
        "Date": "2023-04-27T00:00:00",
        "Open": 163.54072434320634,
        "High": 166.8770729984066,
        "Low": 163.54072434320634,
        "Close": 166.72857666015625,
        "Volume": 64902300,
        "ShortEMA": 163.41678872432385,
        "LongEMA": 161.01414622538687,
        "TrendFilterMA": 156.0423568725586,
        "SignalUnfiltered": "hold",
        "SignalFiltered": "hold"
    },
    {
        "Date": "2023-04-28T00:00:00",
        "Open": 166.80779457565893,
        "High": 168.15421688581486,
        "Low": 166.2038842356674,
        "Close": 167.98590087890625,
        "Volume": 55209200,
        "ShortEMA": 164.11972905579808,
        "LongEMA": 161.53057249601792,
        "TrendFilterMA": 156.32649139404296,
        "SignalUnfiltered": "hold",
        "SignalFiltered": "hold"
    },
    {
        "Date": "2023-05-01T00:00:00",
        "Open": 167.58988704485296,
        "High": 168.74820381228082,
        "Low": 166.9562774855819,
        "Close": 167.89678955078125,
        "Volume": 52472900,
        "ShortEMA": 164.7008152857955,
        "LongEMA": 162.0021441297041,
        "TrendFilterMA": 156.64092010498047,
        "SignalUnfiltered": "hold",
        "SignalFiltered": "hold"
    },
    {
        "Date": "2023-05-02T00:00:00",
        "Open": 168.3918123170909,
        "High": 168.6492261368123,
        "Low": 165.86726857821876,
        "Close": 166.85728454589844,
        "Volume": 48425700,
        "ShortEMA": 165.0325797873498,
        "LongEMA": 162.36178416053332,
        "TrendFilterMA": 156.95752685546876,
        "SignalUnfiltered": "hold",
        "SignalFiltered": "hold"
    },
    {
        "Date": "2023-05-03T00:00:00",
        "Open": 167.80771888799373,
        "High": 169.21353985292495,
        "Low": 165.4910849784499,
        "Close": 165.77818298339844,
        "Volume": 65136000,
        "ShortEMA": 165.1472879713573,
        "LongEMA": 162.6148507400048,
        "TrendFilterMA": 157.33313903808593,
        "SignalUnfiltered": "hold",
        "SignalFiltered": "hold"
    },
    {
        "Date": "2023-05-04T00:00:00",
        "Open": 163.24372680909343,
        "High": 165.3722550253471,
        "Low": 162.66951575440282,
        "Close": 164.13473510742188,
        "Volume": 81235400,
        "ShortEMA": 164.9915106076749,
        "LongEMA": 162.7274347672209,
        "TrendFilterMA": 157.6673681640625,
        "SignalUnfiltered": "hold",
        "SignalFiltered": "hold"
    },
    {
        "Date": "2023-05-05T00:00:00",
        "Open": 169.27291399392053,
        "High": 172.55977402605672,
        "Low": 169.055109287866,
        "Close": 171.83706665039062,
        "Volume": 113316400,
        "ShortEMA": 166.04467307578503,
        "LongEMA": 163.40222231412235,
        "TrendFilterMA": 158.14594177246093,
        "SignalUnfiltered": "hold",
        "SignalFiltered": "hold"
    },
    {
        "Date": "2023-05-08T00:00:00",
        "Open": 170.7579255984111,
        "High": 172.1142575536809,
        "Low": 170.3916245765101,
        "Close": 171.7677459716797,
        "Volume": 55962800,
        "ShortEMA": 166.9251458289996,
        "LongEMA": 164.02189073320068,
        "TrendFilterMA": 158.6763916015625,
        "SignalUnfiltered": "hold",
        "SignalFiltered": "hold"
    },
    {
        "Date": "2023-05-09T00:00:00",
        "Open": 171.32225761857964,
        "High": 171.80735575023974,
        "Low": 169.8867375588741,
        "Close": 170.05503845214844,
        "Volume": 45326900,
        "ShortEMA": 167.4066677710225,
        "LongEMA": 164.46879056423384,
        "TrendFilterMA": 159.1486294555664,
        "SignalUnfiltered": "hold",
        "SignalFiltered": "hold"
    },
    {
        "Date": "2023-05-10T00:00:00",
        "Open": 171.29257694818676,
        "High": 172.29248769554175,
        "Low": 170.1837487273319,
        "Close": 171.82717895507812,
        "Volume": 53724500,
        "ShortEMA": 168.08674641472336,
        "LongEMA": 165.01385637096305,
        "TrendFilterMA": 159.6664077758789,
        "SignalUnfiltered": "hold",
        "SignalFiltered": "hold"
    },
    {
        "Date": "2023-05-11T00:00:00",
        "Open": 172.11425115186051,
        "High": 172.84685316841325,
        "Low": 170.45101676913876,
        "Close": 172.01524353027344,
        "Volume": 49514700,
        "ShortEMA": 168.69113058634645,
        "LongEMA": 165.53247764202308,
        "TrendFilterMA": 160.22952850341798,
        "SignalUnfiltered": "hold",
        "SignalFiltered": "hold"
    },
    {
        "Date": "2023-05-12T00:00:00",
        "Open": 172.12430116865193,
        "High": 172.5605130962495,
        "Low": 169.52687667093326,
        "Close": 171.08335876464844,
        "Volume": 45497800,
        "ShortEMA": 169.0591656907006,
        "LongEMA": 165.94365402147682,
        "TrendFilterMA": 160.7621307373047,
        "SignalUnfiltered": "hold",
        "SignalFiltered": "hold"
    },
    {
        "Date": "2023-05-15T00:00:00",
        "Open": 171.6682987112497,
        "High": 171.71787100649163,
        "Low": 169.99285497252012,
        "Close": 170.5876922607422,
        "Volume": 37266700,
        "ShortEMA": 169.29432362455316,
        "LongEMA": 166.28765685401498,
        "TrendFilterMA": 161.1834423828125,
        "SignalUnfiltered": "hold",
        "SignalFiltered": "hold"
    },
    {
        "Date": "2023-05-16T00:00:00",
        "Open": 170.5083796138232,
        "High": 171.64846676768477,
        "Low": 170.3200139683082,
        "Close": 170.5876922607422,
        "Volume": 42110300,
        "ShortEMA": 169.4933034147361,
        "LongEMA": 166.60617799525403,
        "TrendFilterMA": 161.5493133544922,
        "SignalUnfiltered": "hold",
        "SignalFiltered": "hold"
    },
    {
        "Date": "2023-05-17T00:00:00",
        "Open": 170.23077817517168,
        "High": 171.4402543357864,
        "Low": 168.9518826544196,
        "Close": 171.20233154296875,
        "Volume": 57951600,
        "ShortEMA": 169.75623081907958,
        "LongEMA": 166.94663381360326,
        "TrendFilterMA": 161.97163177490233,
        "SignalUnfiltered": "hold",
        "SignalFiltered": "hold"
    },
    {
        "Date": "2023-05-18T00:00:00",
        "Open": 171.50966446616422,
        "High": 173.73037308197308,
        "Low": 171.0932844370763,
        "Close": 173.54200744628906,
        "Volume": 65496700,
        "ShortEMA": 170.33865799249642,
        "LongEMA": 167.435180008617,
        "TrendFilterMA": 162.41559753417968,
        "SignalUnfiltered": "hold",
        "SignalFiltered": "hold"
    },
    {
        "Date": "2023-05-19T00:00:00",
        "Open": 174.87044639396197,
        "High": 174.87044639396197,
        "Low": 173.43294078431077,
        "Close": 173.6510467529297,
        "Volume": 55772400,
        "ShortEMA": 170.8482562633323,
        "LongEMA": 167.8956145822698,
        "TrendFilterMA": 162.90688842773437,
        "SignalUnfiltered": "hold",
        "SignalFiltered": "hold"
    },
    {
        "Date": "2023-05-22T00:00:00",
        "Open": 172.481219573557,
        "High": 173.20494177332736,
        "Low": 171.95578654636702,
        "Close": 172.69932556152344,
        "Volume": 43570900,
        "ShortEMA": 171.1330361553617,
        "LongEMA": 168.25144502517747,
        "TrendFilterMA": 163.42052795410157,
        "SignalUnfiltered": "hold",
        "SignalFiltered": "hold"
    },
    {
        "Date": "2023-05-23T00:00:00",
        "Open": 171.6385439691014,
        "High": 171.88639029719062,
        "Low": 169.80447509030535,
        "Close": 170.08206176757812,
        "Volume": 50747300,
        "ShortEMA": 170.97134778801038,
        "LongEMA": 168.3870462653553,
        "TrendFilterMA": 163.84281494140626,
        "SignalUnfiltered": "hold",
        "SignalFiltered": "hold"
    },
    {
        "Date": "2023-05-24T00:00:00",
        "Open": 169.61611066863975,
        "High": 170.93465495874622,
        "Low": 169.0510289027881,
        "Close": 170.35964965820312,
        "Volume": 45143500,
        "ShortEMA": 170.87724038342463,
        "LongEMA": 168.53316503519588,
        "TrendFilterMA": 164.22867736816406,
        "SignalUnfiltered": "hold",
        "SignalFiltered": "hold"
    },
    {
        "Date": "2023-05-25T00:00:00",
        "Open": 170.92476575302507,
        "High": 172.40192036340346,
        "Low": 170.21096703266915,
        "Close": 171.49977111816406,
        "Volume": 56058300,
        "ShortEMA": 170.97301434261533,
        "LongEMA": 168.75291363393427,
        "TrendFilterMA": 164.62942199707032,
        "SignalUnfiltered": "hold",
        "SignalFiltered": "hold"
    },
    {
        "Date": "2023-05-26T00:00:00",
        "Open": 171.826923039006,
        "High": 174.25581421879875,
        "Low": 171.61872545109665,
        "Close": 173.91873168945312,
        "Volume": 54835000,
        "ShortEMA": 171.42620162674422,
        "LongEMA": 169.13556682323195,
        "TrendFilterMA": 165.02191680908203,
        "SignalUnfiltered": "hold",
        "SignalFiltered": "hold"
    },
    {
        "Date": "2023-05-30T00:00:00",
        "Open": 175.43556138959772,
        "High": 177.44807247659148,
        "Low": 175.04892170114425,
        "Close": 175.7726287841797,
        "Volume": 55964400,
        "ShortEMA": 172.09488272788812,
        "LongEMA": 169.6272010425614,
        "TrendFilterMA": 165.46831970214845,
        "SignalUnfiltered": "hold",
        "SignalFiltered": "hold"
    },
    {
        "Date": "2023-05-31T00:00:00",
        "Open": 175.80236562165695,
        "High": 177.80496826079084,
        "Low": 175.23726871202743,
        "Close": 175.72305297851562,
        "Volume": 99625300,
        "ShortEMA": 172.6530627664462,
        "LongEMA": 170.07874563040986,
        "TrendFilterMA": 165.86621032714845,
        "SignalUnfiltered": "hold",
        "SignalFiltered": "hold"
    },
    {
        "Date": "2023-06-01T00:00:00",
        "Open": 176.1691489115404,
        "High": 178.56829930609416,
        "Low": 175.4057780636658,
        "Close": 178.53855895996094,
        "Volume": 68901800,
        "ShortEMA": 173.5585237192946,
        "LongEMA": 170.70539846963587,
        "TrendFilterMA": 166.2831869506836,
        "SignalUnfiltered": "hold",
        "SignalFiltered": "hold"
    },
    {
        "Date": "2023-06-02T00:00:00",
        "Open": 179.47047169338217,
        "High": 180.21401063542314,
        "Low": 177.7157155545107,
        "Close": 179.3911590576172,
        "Volume": 61945900,
        "ShortEMA": 174.4558522328827,
        "LongEMA": 171.34878814281967,
        "TrendFilterMA": 166.74592559814454,
        "SignalUnfiltered": "hold",
        "SignalFiltered": "hold"
    },
    {
        "Date": "2023-06-05T00:00:00",
        "Open": 181.05670243794387,
        "High": 183.35670847100744,
        "Low": 176.50623240767692,
        "Close": 178.03297424316406,
        "Volume": 121946500,
        "ShortEMA": 175.0061786960029,
        "LongEMA": 171.84391303914148,
        "TrendFilterMA": 167.15972045898437,
        "SignalUnfiltered": "hold",
        "SignalFiltered": "hold"
    },
    {
        "Date": "2023-06-06T00:00:00",
        "Open": 178.41963092679066,
        "High": 178.56833268525313,
        "Low": 175.9015035496613,
        "Close": 177.6661834716797,
        "Volume": 64848400,
        "ShortEMA": 175.4154101999532,
        "LongEMA": 172.2751923304406,
        "TrendFilterMA": 167.54004333496093,
        "SignalUnfiltered": "hold",
        "SignalFiltered": "hold"
    },
    {
        "Date": "2023-06-07T00:00:00",
        "Open": 176.90281634965245,
        "High": 179.6489581922576,
        "Low": 175.79246952260962,
        "Close": 176.2881622314453,
        "Volume": 61944600,
        "ShortEMA": 175.54967974325967,
        "LongEMA": 172.57244936014465,
        "TrendFilterMA": 167.93181213378907,
        "SignalUnfiltered": "hold",
        "SignalFiltered": "hold"
    },
    {
        "Date": "2023-06-08T00:00:00",
        "Open": 176.36743802214428,
        "High": 179.28211321134853,
        "Low": 175.93124119908015,
        "Close": 179.0144500732422,
        "Volume": 50214900,
        "ShortEMA": 176.08272133248775,
        "LongEMA": 173.04963459815187,
        "TrendFilterMA": 168.3905807495117,
        "SignalUnfiltered": "hold",
        "SignalFiltered": "hold"
    },
    {
        "Date": "2023-06-09T00:00:00",
        "Open": 179.93644924551378,
        "High": 180.66015634842165,
        "Low": 179.0739487923587,
        "Close": 179.40110778808594,
        "Volume": 48870700,
        "ShortEMA": 176.5932423256567,
        "LongEMA": 173.52011409370255,
        "TrendFilterMA": 168.79530548095704,
        "SignalUnfiltered": "hold",
        "SignalFiltered": "hold"
    },
    {
        "Date": "2023-06-12T00:00:00",
        "Open": 179.70841552076647,
        "High": 182.30584013644759,
        "Low": 179.4109969086846,
        "Close": 182.20669555664062,
        "Volume": 54274900,
        "ShortEMA": 177.45685051503884,
        "LongEMA": 174.1635645724387,
        "TrendFilterMA": 169.22465972900392,
        "SignalUnfiltered": "hold",
        "SignalFiltered": "hold"
    },
    {
        "Date": "2023-06-13T00:00:00",
        "Open": 181.2252339092373,
        "High": 182.5635949733869,
        "Low": 180.86833459999627,
        "Close": 181.7308349609375,
        "Volume": 54929100,
        "ShortEMA": 178.11438658363863,
        "LongEMA": 174.7241031197349,
        "TrendFilterMA": 169.59420379638672,
        "SignalUnfiltered": "hold",
        "SignalFiltered": "hold"
    },
    {
        "Date": "2023-06-14T00:00:00",
        "Open": 181.79032062893717,
        "High": 182.8015378873281,
        "Low": 180.45195952819037,
        "Close": 182.36532592773438,
        "Volume": 57462900,
        "ShortEMA": 178.76837725196106,
        "LongEMA": 175.29011962403115,
        "TrendFilterMA": 169.95129119873047,
        "SignalUnfiltered": "hold",
        "SignalFiltered": "hold"
    },
    {
        "Date": "2023-06-15T00:00:00",
        "Open": 182.37524971506843,
        "High": 184.91319370821412,
        "Low": 182.19679249165128,
        "Close": 184.40757751464844,
        "Volume": 65433200,
        "ShortEMA": 179.63594652314373,
        "LongEMA": 175.965486875188,
        "TrendFilterMA": 170.35991577148437,
        "SignalUnfiltered": "hold",
        "SignalFiltered": "hold"
    },
    {
        "Date": "2023-06-16T00:00:00",
        "Open": 185.12135487176403,
        "High": 185.37912470625074,
        "Low": 182.68255574170084,
        "Close": 183.3269500732422,
        "Volume": 101235600,
        "ShortEMA": 180.20379322315887,
        "LongEMA": 176.51078044541424,
        "TrendFilterMA": 170.78395416259767,
        "SignalUnfiltered": "hold",
        "SignalFiltered": "hold"
    },
    {
        "Date": "2023-06-20T00:00:00",
        "Open": 182.82137659501507,
        "High": 184.4968202621219,
        "Low": 182.82137659501507,
        "Close": 183.41619873046875,
        "Volume": 49799100,
        "ShortEMA": 180.6980094550527,
        "LongEMA": 177.02229291097385,
        "TrendFilterMA": 171.19195770263673,
        "SignalUnfiltered": "hold",
        "SignalFiltered": "hold"
    },
    {
        "Date": "2023-06-21T00:00:00",
        "Open": 183.3071642774052,
        "High": 183.8127805401231,
        "Low": 181.0170663004923,
        "Close": 182.37527465820312,
        "Volume": 49515700,
        "ShortEMA": 180.95605025553738,
        "LongEMA": 177.41881007743527,
        "TrendFilterMA": 171.6312176513672,
        "SignalUnfiltered": "hold",
        "SignalFiltered": "hold"
    },
    {
        "Date": "2023-06-22T00:00:00",
        "Open": 182.15715766621673,
        "High": 185.43864089866383,
        "Low": 182.08775342754114,
        "Close": 185.38906860351562,
        "Volume": 51245300,
        "ShortEMA": 181.63805307830327,
        "LongEMA": 178.00919959788567,
        "TrendFilterMA": 172.1551071166992,
        "SignalUnfiltered": "hold",
        "SignalFiltered": "hold"
    },
    {
        "Date": "2023-06-23T00:00:00",
        "Open": 183.9515678810459,
        "High": 185.94424713129428,
        "Low": 183.41621128242684,
        "Close": 185.0718231201172,
        "Volume": 53079300,
        "ShortEMA": 182.1663253924285,
        "LongEMA": 178.53235689582874,
        "TrendFilterMA": 172.6865121459961,
        "SignalUnfiltered": "hold",
        "SignalFiltered": "hold"
    },
    {
        "Date": "2023-06-26T00:00:00",
        "Open": 185.2205087707664,
        "High": 186.42999999051133,
        "Low": 183.63428631385352,
        "Close": 183.6739501953125,
        "Volume": 48088700,
        "ShortEMA": 182.39826766979527,
        "LongEMA": 178.91321565875347,
        "TrendFilterMA": 173.0818505859375,
        "SignalUnfiltered": "hold",
        "SignalFiltered": "hold"
    },
    {
        "Date": "2023-06-27T00:00:00",
        "Open": 184.28862175731683,
        "High": 186.767085127622,
        "Low": 184.07051577054278,
        "Close": 186.43992614746094,
        "Volume": 50730800,
        "ShortEMA": 183.02006128174384,
        "LongEMA": 179.4707497690281,
        "TrendFilterMA": 173.5394381713867,
        "SignalUnfiltered": "hold",
        "SignalFiltered": "hold"
    },
    {
        "Date": "2023-06-28T00:00:00",
        "Open": 186.31106908377777,
        "High": 188.26409972194077,
        "Low": 185.98392518201555,
        "Close": 187.6197052001953,
        "Volume": 51216800,
        "ShortEMA": 183.72769880765944,
        "LongEMA": 180.0743760972627,
        "TrendFilterMA": 174.02022583007812,
        "SignalUnfiltered": "hold",
        "SignalFiltered": "hold"
    },
    {
        "Date": "2023-06-29T00:00:00",
        "Open": 187.45114025988062,
        "High": 188.43261718372244,
        "Low": 187.31234691859044,
        "Close": 187.9567413330078,
        "Volume": 46347300,
        "ShortEMA": 184.3783207346361,
        "LongEMA": 180.6582550036142,
        "TrendFilterMA": 174.48320098876954,
        "SignalUnfiltered": "hold",
        "SignalFiltered": "hold"
    },
    {
        "Date": "2023-06-30T00:00:00",
        "Open": 189.97918829297507,
        "High": 192.80462759541973,
        "Low": 189.6123654098311,
        "Close": 192.2990264892578,
        "Volume": 85069600,
        "ShortEMA": 185.59689085073174,
        "LongEMA": 181.52053437292113,
        "TrendFilterMA": 175.0100537109375,
        "SignalUnfiltered": "hold",
        "SignalFiltered": "hold"
    },
    {
        "Date": "2023-07-03T00:00:00",
        "Open": 192.11062254888682,
        "High": 192.20976711966864,
        "Low": 190.10802021232752,
        "Close": 190.802001953125,
        "Volume": 31458200,
        "ShortEMA": 186.39767717417686,
        "LongEMA": 182.20805048997326,
        "TrendFilterMA": 175.5263705444336,
        "SignalUnfiltered": "hold",
        "SignalFiltered": "hold"
    },
    {
        "Date": "2023-07-05T00:00:00",
        "Open": 189.91968534956396,
        "High": 191.3175270975779,
        "Low": 188.97785723169864,
        "Close": 189.68174743652344,
        "Volume": 46920300,
        "ShortEMA": 186.90291875299943,
        "LongEMA": 182.7616576711992,
        "TrendFilterMA": 176.0525570678711,
        "SignalUnfiltered": "hold",
        "SignalFiltered": "hold"
    },
    {
        "Date": "2023-07-06T00:00:00",
        "Open": 188.20457782150964,
        "High": 190.36580559694158,
        "Low": 187.57009184775086,
        "Close": 190.15760803222656,
        "Volume": 45094300,
        "ShortEMA": 187.40364018057284,
        "LongEMA": 183.3095058460901,
        "TrendFilterMA": 176.58212219238283,
        "SignalUnfiltered": "hold",
        "SignalFiltered": "hold"
    },
    {
        "Date": "2023-07-07T00:00:00",
        "Open": 189.76107572138073,
        "High": 191.01021583133178,
        "Low": 188.60115666342472,
        "Close": 189.037353515625,
        "Volume": 46778000,
        "ShortEMA": 187.6549806936578,
        "LongEMA": 183.73379085864823,
        "TrendFilterMA": 177.12017059326172,
        "SignalUnfiltered": "hold",
        "SignalFiltered": "hold"
    },
    {
        "Date": "2023-07-10T00:00:00",
        "Open": 187.62959342704087,
        "High": 188.35331565327752,
        "Low": 185.42871665150543,
        "Close": 186.98519897460938,
        "Volume": 59922200,
        "ShortEMA": 187.55193735226572,
        "LongEMA": 183.97463590427498,
        "TrendFilterMA": 177.61737396240235,
        "SignalUnfiltered": "hold",
        "SignalFiltered": "hold"
    },
    {
        "Date": "2023-07-11T00:00:00",
        "Open": 187.53046059023825,
        "High": 187.66925393721883,
        "Low": 184.99251645839882,
        "Close": 186.4597625732422,
        "Volume": 46638100,
        "ShortEMA": 187.38391046318517,
        "LongEMA": 184.1587193612355,
        "TrendFilterMA": 178.01199768066405,
        "SignalUnfiltered": "hold",
        "SignalFiltered": "hold"
    },
    {
        "Date": "2023-07-12T00:00:00",
        "Open": 188.04597194874682,
        "High": 190.04857465553215,
        "Low": 186.84640410814296,
        "Close": 188.1352081298828,
        "Volume": 60750200,
        "ShortEMA": 187.4994947196002,
        "LongEMA": 184.45327408483902,
        "TrendFilterMA": 178.4149838256836,
        "SignalUnfiltered": "hold",
        "SignalFiltered": "hold"
    },
    {
        "Date": "2023-07-13T00:00:00",
        "Open": 188.85892606758472,
        "High": 189.54298444064506,
        "Low": 188.14512734155142,
        "Close": 188.89857482910156,
        "Volume": 41342300,
        "ShortEMA": 187.71473781336962,
        "LongEMA": 184.78255562145105,
        "TrendFilterMA": 178.83501953125,
        "SignalUnfiltered": "hold",
        "SignalFiltered": "hold"
    },
    {
        "Date": "2023-07-14T00:00:00",
        "Open": 188.59122781892412,
        "High": 189.53304086059518,
        "Low": 187.99640569502964,
        "Close": 189.04727172851562,
        "Volume": 41573900,
        "ShortEMA": 187.91974303108438,
        "LongEMA": 185.09846051827066,
        "TrendFilterMA": 179.27881927490233,
        "SignalUnfiltered": "hold",
        "SignalFiltered": "hold"
    },
    {
        "Date": "2023-07-17T00:00:00",
        "Open": 190.24684079775338,
        "High": 192.64600663390738,
        "Low": 190.15761974766676,
        "Close": 192.31884765625,
        "Volume": 50520200,
        "ShortEMA": 188.59652835803294,
        "LongEMA": 185.63330400997282,
        "TrendFilterMA": 179.80963256835938,
        "SignalUnfiltered": "hold",
        "SignalFiltered": "hold"
    },
    {
        "Date": "2023-07-18T00:00:00",
        "Open": 191.68434955477355,
        "High": 192.65590289157154,
        "Low": 190.76235338000512,
        "Close": 192.06106567382812,
        "Volume": 48353800,
        "ShortEMA": 189.1295340989245,
        "LongEMA": 186.10943450359173,
        "TrendFilterMA": 180.3681591796875,
        "SignalUnfiltered": "hold",
        "SignalFiltered": "hold"
    },
    {
        "Date": "2023-07-19T00:00:00",
        "Open": 191.43649527350667,
        "High": 196.52229125160747,
        "Low": 190.99035981508428,
        "Close": 193.4192657470703,
        "Volume": 80507300,
        "ShortEMA": 189.78949281402384,
        "LongEMA": 186.65090348459015,
        "TrendFilterMA": 180.7998031616211,
        "SignalUnfiltered": "hold",
        "SignalFiltered": "hold"
    },
    {
        "Date": "2023-07-20T00:00:00",
        "Open": 193.40935427253197,
        "High": 194.777470825343,
        "Low": 190.84166997972974,
        "Close": 191.46624755859375,
        "Volume": 59581200,
        "ShortEMA": 190.04745508241922,
        "LongEMA": 187.00759563822004,
        "TrendFilterMA": 181.19377319335936,
        "SignalUnfiltered": "hold",
        "SignalFiltered": "hold"
    },
    {
        "Date": "2023-07-21T00:00:00",
        "Open": 192.42789492586837,
        "High": 193.29039530573385,
        "Low": 189.58260879656223,
        "Close": 190.2864990234375,
        "Volume": 71917800,
        "ShortEMA": 190.0842310733451,
        "LongEMA": 187.25047737045836,
        "TrendFilterMA": 181.59840240478516,
        "SignalUnfiltered": "hold",
        "SignalFiltered": "hold"
    },
    {
        "Date": "2023-07-24T00:00:00",
        "Open": 191.74382595603396,
        "High": 193.2309038397432,
        "Low": 190.59381542873754,
        "Close": 191.08950805664062,
        "Volume": 45377800,
        "ShortEMA": 190.2388890707752,
        "LongEMA": 187.53485001387926,
        "TrendFilterMA": 181.9836489868164,
        "SignalUnfiltered": "hold",
        "SignalFiltered": "hold"
    },
    {
        "Date": "2023-07-25T00:00:00",
        "Open": 191.66453127210508,
        "High": 192.7649696142135,
        "Low": 191.25805964859208,
        "Close": 191.9520263671875,
        "Volume": 37283200,
        "ShortEMA": 190.50244865483864,
        "LongEMA": 187.86204826227248,
        "TrendFilterMA": 182.3823846435547,
        "SignalUnfiltered": "hold",
        "SignalFiltered": "hold"
    },
    {
        "Date": "2023-07-26T00:00:00",
        "Open": 192.0015807949404,
        "High": 193.95461096026835,
        "Low": 191.65460503159764,
        "Close": 192.82443237304688,
        "Volume": 47471900,
        "ShortEMA": 190.85967691917838,
        "LongEMA": 188.229632270478,
        "TrendFilterMA": 182.81720611572266,
        "SignalUnfiltered": "hold",
        "SignalFiltered": "hold"
    },
    {
        "Date": "2023-07-27T00:00:00",
        "Open": 194.33134751765755,
        "High": 195.50117489112708,
        "Low": 190.89123937354253,
        "Close": 191.5554656982422,
        "Volume": 47460200,
        "ShortEMA": 190.96672134672667,
        "LongEMA": 188.47599030216423,
        "TrendFilterMA": 183.23656158447267,
        "SignalUnfiltered": "hold",
        "SignalFiltered": "hold"
    },
    {
        "Date": "2023-07-28T00:00:00",
        "Open": 192.9930098409439,
        "High": 194.93613204043868,
        "Low": 192.4675767460108,
        "Close": 194.1430206298828,
        "Volume": 48291400,
        "ShortEMA": 191.45538277490454,
        "LongEMA": 188.89577032643967,
        "TrendFilterMA": 183.70766815185547,
        "SignalUnfiltered": "hold",
        "SignalFiltered": "hold"
    },
    {
        "Date": "2023-07-31T00:00:00",
        "Open": 194.37098975201062,
        "High": 194.79729327585247,
        "Low": 193.5778785263088,
        "Close": 194.75762939453125,
        "Volume": 38824100,
        "ShortEMA": 191.96342071638557,
        "LongEMA": 189.32998210926127,
        "TrendFilterMA": 184.17877410888673,
        "SignalUnfiltered": "hold",
        "SignalFiltered": "hold"
    },
    {
        "Date": "2023-08-01T00:00:00",
        "Open": 194.54944325919743,
        "High": 195.0352123410956,
        "Low": 193.59770678100793,
        "Close": 193.92486572265625,
        "Volume": 35175100,
        "ShortEMA": 192.26518148658107,
        "LongEMA": 189.67034385840162,
        "TrendFilterMA": 184.58643127441405,
        "SignalUnfiltered": "hold",
        "SignalFiltered": "hold"
    },
    {
        "Date": "2023-08-02T00:00:00",
        "Open": 193.3598049013339,
        "High": 193.49859825449514,
        "Low": 190.19729813092133,
        "Close": 190.92100524902344,
        "Volume": 50389300,
        "ShortEMA": 192.05838514234142,
        "LongEMA": 189.76298544289213,
        "TrendFilterMA": 184.93183044433593,
        "SignalUnfiltered": "hold",
        "SignalFiltered": "hold"
    },
    {
        "Date": "2023-08-03T00:00:00",
        "Open": 189.91968024316816,
        "High": 190.71277634396813,
        "Low": 189.047256379482,
        "Close": 189.5231170654297,
        "Volume": 61235200,
        "ShortEMA": 191.66834389973963,
        "LongEMA": 189.74521741493194,
        "TrendFilterMA": 185.26830627441407,
        "SignalUnfiltered": "hold",
        "SignalFiltered": "hold"
    },
    {
        "Date": "2023-08-04T00:00:00",
        "Open": 183.92181504025928,
        "High": 185.76579240309633,
        "Low": 180.35282171627148,
        "Close": 180.42222595214844,
        "Volume": 115799700,
        "ShortEMA": 189.9381719078025,
        "LongEMA": 189.05462545472577,
        "TrendFilterMA": 185.47510955810546,
        "SignalUnfiltered": "hold",
        "SignalFiltered": "hold"
    },
    {
        "Date": "2023-08-07T00:00:00",
        "Open": 180.56102321579414,
        "High": 181.5524085909385,
        "Low": 175.82220233279125,
        "Close": 177.3092803955078,
        "Volume": 97576100,
        "ShortEMA": 187.99526552129564,
        "LongEMA": 188.1845998947837,
        "TrendFilterMA": 185.61410217285157,
        "SignalUnfiltered": "sell",
        "SignalFiltered": "hold"
    },
    {
        "Date": "2023-08-08T00:00:00",
        "Open": 178.1420151343907,
        "High": 178.71702038544473,
        "Low": 176.05019168536276,
        "Close": 178.25106811523438,
        "Volume": 67823000,
        "ShortEMA": 186.49615822805544,
        "LongEMA": 187.4487827259282,
        "TrendFilterMA": 185.74912811279296,
        "SignalUnfiltered": "hold",
        "SignalFiltered": "hold"
    },
    {
        "Date": "2023-08-09T00:00:00",
        "Open": 179.31185840559957,
        "High": 179.3713391045639,
        "Low": 175.48511045638642,
        "Close": 176.6549530029297,
        "Volume": 60378500,
        "ShortEMA": 184.98212665495916,
        "LongEMA": 186.64923978348386,
        "TrendFilterMA": 185.8038525390625,
        "SignalUnfiltered": "hold",
        "SignalFiltered": "hold"
    },
    {
        "Date": "2023-08-10T00:00:00",
        "Open": 177.93381484794008,
        "High": 179.19287831156532,
        "Low": 176.07002092304583,
        "Close": 176.43682861328125,
        "Volume": 54686900,
        "ShortEMA": 183.66746541777795,
        "LongEMA": 185.89276488198738,
        "TrendFilterMA": 185.81713653564452,
        "SignalUnfiltered": "hold",
        "SignalFiltered": "hold"
    },
    {
        "Date": "2023-08-11T00:00:00",
        "Open": 176.02983256684112,
        "High": 177.32036168980022,
        "Low": 175.26543082107975,
        "Close": 176.49639892578125,
        "Volume": 51988100,
        "ShortEMA": 182.56422441900924,
        "LongEMA": 185.19673777412027,
        "TrendFilterMA": 185.83260345458984,
        "SignalUnfiltered": "hold",
        "SignalFiltered": "hold"
    },
    {
        "Date": "2023-08-14T00:00:00",
        "Open": 176.6751020557822,
        "High": 178.38258864969947,
        "Low": 176.01990054114177,
        "Close": 178.15426635742188,
        "Volume": 43675600,
        "ShortEMA": 181.88576933261118,
        "LongEMA": 184.6750732247352,
        "TrendFilterMA": 185.82491760253907,
        "SignalUnfiltered": "hold",
        "SignalFiltered": "hold"
    },
    {
        "Date": "2023-08-15T00:00:00",
        "Open": 177.57847773870674,
        "High": 178.174103062697,
        "Low": 175.76179096239193,
        "Close": 176.15887451171875,
        "Volume": 43622600,
        "ShortEMA": 181.00470859093542,
        "LongEMA": 184.0442436904377,
        "TrendFilterMA": 185.7602719116211,
        "SignalUnfiltered": "hold",
        "SignalFiltered": "hold"
    },
    {
        "Date": "2023-08-16T00:00:00",
        "Open": 175.84123193317788,
        "High": 177.24096145960885,
        "Low": 175.2158108770956,
        "Close": 175.28530883789062,
        "Volume": 46964900,
        "ShortEMA": 180.12480093662083,
        "LongEMA": 183.39543370136013,
        "TrendFilterMA": 185.70531860351562,
        "SignalUnfiltered": "hold",
        "SignalFiltered": "hold"
    },
    {
        "Date": "2023-08-17T00:00:00",
        "Open": 175.85113106656488,
        "High": 176.2184341041098,
        "Low": 172.21775754332145,
        "Close": 172.73397827148438,
        "Volume": 66062900,
        "ShortEMA": 178.9877512958306,
        "LongEMA": 182.6056962621101,
        "TrendFilterMA": 185.6066744995117,
        "SignalUnfiltered": "hold",
        "SignalFiltered": "hold"
    },
    {
        "Date": "2023-08-18T00:00:00",
        "Open": 171.04636032936088,
        "High": 173.82599075554495,
        "Low": 170.70883778094841,
        "Close": 173.22042846679688,
        "Volume": 61114200,
        "ShortEMA": 178.10047086059464,
        "LongEMA": 181.91049124023505,
        "TrendFilterMA": 185.54531982421875,
        "SignalUnfiltered": "hold",
        "SignalFiltered": "hold"
    },
    {
        "Date": "2023-08-21T00:00:00",
        "Open": 173.79620604217206,
        "High": 174.84849110751958,
        "Low": 172.47588124297116,
        "Close": 174.5605926513672,
        "Volume": 46311900,
        "ShortEMA": 177.55587421302118,
        "LongEMA": 181.36605430772633,
        "TrendFilterMA": 185.45624267578125,
        "SignalUnfiltered": "hold",
        "SignalFiltered": "hold"
    },
    {
        "Date": "2023-08-22T00:00:00",
        "Open": 175.77172944077836,
        "High": 176.38721354501158,
        "Low": 174.96762533098521,
        "Close": 175.94049072265625,
        "Volume": 42084200,
        "ShortEMA": 177.30735367604197,
        "LongEMA": 180.96416070883225,
        "TrendFilterMA": 185.38703033447266,
        "SignalUnfiltered": "hold",
        "SignalFiltered": "hold"
    },
    {
        "Date": "2023-08-23T00:00:00",
        "Open": 177.2210964343875,
        "High": 180.22904900558675,
        "Low": 177.03247644679308,
        "Close": 179.8021697998047,
        "Volume": 52722800,
        "ShortEMA": 177.69117154123623,
        "LongEMA": 180.87808730816354,
        "TrendFilterMA": 185.33893981933593,
        "SignalUnfiltered": "hold",
        "SignalFiltered": "hold"
    },
    {
        "Date": "2023-08-24T00:00:00",
        "Open": 179.355459364837,
        "High": 179.78233860000068,
        "Low": 174.72936147404116,
        "Close": 175.0966796875,
        "Volume": 54945800,
        "ShortEMA": 177.29201894835373,
        "LongEMA": 180.44983489181809,
        "TrendFilterMA": 185.2062567138672,
        "SignalUnfiltered": "hold",
        "SignalFiltered": "hold"
    },
    {
        "Date": "2023-08-25T00:00:00",
        "Open": 176.08940889849805,
        "High": 177.84651968096887,
        "Low": 174.54076169805765,
        "Close": 177.31045532226562,
        "Volume": 51449600,
        "ShortEMA": 177.29485531357093,
        "LongEMA": 180.21728825703642,
        "TrendFilterMA": 185.10515930175782,
        "SignalUnfiltered": "hold",
        "SignalFiltered": "hold"
    },
    {
        "Date": "2023-08-28T00:00:00",
        "Open": 178.77968881089737,
        "High": 179.27605088665493,
        "Low": 177.25090028258217,
        "Close": 178.87896728515625,
        "Volume": 43820700,
        "ShortEMA": 177.53856484766098,
        "LongEMA": 180.1181533702305,
        "TrendFilterMA": 184.99458709716797,
        "SignalUnfiltered": "hold",
        "SignalFiltered": "hold"
    },
    {
        "Date": "2023-08-29T00:00:00",
        "Open": 178.39251118833664,
        "High": 183.55467328918405,
        "Low": 178.19396940518234,
        "Close": 182.7803497314453,
        "Volume": 53003900,
        "ShortEMA": 178.3449932913201,
        "LongEMA": 180.31535310069086,
        "TrendFilterMA": 184.98365509033204,
        "SignalUnfiltered": "hold",
        "SignalFiltered": "hold"
    },
    {
        "Date": "2023-08-30T00:00:00",
        "Open": 183.59439418869403,
        "High": 186.48322490340712,
        "Low": 183.39585240180426,
        "Close": 186.28466796875,
        "Volume": 60813900,
        "ShortEMA": 179.5664817032324,
        "LongEMA": 180.75752457239895,
        "TrendFilterMA": 185.04102447509766,
        "SignalUnfiltered": "hold",
        "SignalFiltered": "hold"
    },
    {
        "Date": "2023-08-31T00:00:00",
        "Open": 186.4732559934848,
        "High": 187.7439413890159,
        "Low": 186.1158747792564,
        "Close": 186.50303649902344,
        "Volume": 60794500,
        "ShortEMA": 180.63364397950795,
        "LongEMA": 181.1831180484452,
        "TrendFilterMA": 185.12357971191406,
        "SignalUnfiltered": "hold",
        "SignalFiltered": "hold"
    },
    {
        "Date": "2023-09-01T00:00:00",
        "Open": 188.11127770079705,
        "High": 188.538141753245,
        "Low": 186.91007498628073,
        "Close": 188.0814971923828,
        "Volume": 45732600,
        "ShortEMA": 181.77946755071946,
        "LongEMA": 181.6941090961443,
        "TrendFilterMA": 185.1774282836914,
        "SignalUnfiltered": "buy",
        "SignalFiltered": "hold"
    },
    {
        "Date": "2023-09-05T00:00:00",
        "Open": 186.91009674606673,
        "High": 188.59772472633045,
        "Low": 186.24497340110617,
        "Close": 188.31976318359375,
        "Volume": 45280000,
        "ShortEMA": 182.78566687885396,
        "LongEMA": 182.18489828780721,
        "TrendFilterMA": 185.24238708496094,
        "SignalUnfiltered": "hold",
        "SignalFiltered": "hold"
    },
    {
        "Date": "2023-09-06T00:00:00",
        "Open": 187.02922374370715,
        "High": 187.47596172928527,
        "Low": 180.14965265723944,
        "Close": 181.5791778564453,
        "Volume": 81755800,
        "ShortEMA": 182.6000531830988,
        "LongEMA": 182.14003010770634,
        "TrendFilterMA": 185.2004916381836,
        "SignalUnfiltered": "hold",
        "SignalFiltered": "hold"
    },
    {
        "Date": "2023-09-07T00:00:00",
        "Open": 173.90539355501954,
        "High": 176.91336139268128,
        "Low": 172.27732670257566,
        "Close": 176.26808166503906,
        "Volume": 112488800,
        "ShortEMA": 181.6259037187819,
        "LongEMA": 181.70507096380507,
        "TrendFilterMA": 184.99705474853516,
        "SignalUnfiltered": "sell",
        "SignalFiltered": "sell"
    },
    {
        "Date": "2023-09-08T00:00:00",
        "Open": 177.05235186894313,
        "High": 178.9285998393183,
        "Low": 176.4964136407334,
        "Close": 176.88357543945312,
        "Volume": 65551300,
        "ShortEMA": 180.8963147527313,
        "LongEMA": 181.3479231471864,
        "TrendFilterMA": 184.7823321533203,
        "SignalUnfiltered": "hold",
        "SignalFiltered": "hold"
    },
    {
        "Date": "2023-09-11T00:00:00",
        "Open": 178.7598181226865,
        "High": 178.98814040153138,
        "Low": 176.0496706936909,
        "Close": 178.0549774169922,
        "Volume": 58953100,
        "ShortEMA": 180.45918593184837,
        "LongEMA": 181.1040012412461,
        "TrendFilterMA": 184.584296875,
        "SignalUnfiltered": "hold",
        "SignalFiltered": "hold"
    },
    {
        "Date": "2023-09-12T00:00:00",
        "Open": 178.18404991763566,
        "High": 178.81939272059032,
        "Low": 173.5480302988034,
        "Close": 175.0172576904297,
        "Volume": 90370200,
        "ShortEMA": 179.62196620239934,
        "LongEMA": 180.65313134859304,
        "TrendFilterMA": 184.23866149902344,
        "SignalUnfiltered": "hold",
        "SignalFiltered": "hold"
    },
    {
        "Date": "2023-09-13T00:00:00",
        "Open": 175.22572770658326,
        "High": 176.00998823848755,
        "Low": 172.7141369128852,
        "Close": 172.94247436523438,
        "Volume": 84267900,
        "ShortEMA": 178.59435207360474,
        "LongEMA": 180.08197157204796,
        "TrendFilterMA": 183.88147094726563,
        "SignalUnfiltered": "hold",
        "SignalFiltered": "hold"
    },
    {
        "Date": "2023-09-14T00:00:00",
        "Open": 172.73398888645488,
        "High": 174.81871550108795,
        "Low": 172.3170465930817,
        "Close": 174.46133422851562,
        "Volume": 60895800,
        "ShortEMA": 177.95850317436026,
        "LongEMA": 179.66562806511965,
        "TrendFilterMA": 183.57706268310548,
        "SignalUnfiltered": "hold",
        "SignalFiltered": "hold"
    },
    {
        "Date": "2023-09-15T00:00:00",
        "Open": 175.1959388893145,
        "High": 175.2157976120051,
        "Low": 172.55530438661506,
        "Close": 173.73663330078125,
        "Volume": 109205100,
        "ShortEMA": 177.30898473227117,
        "LongEMA": 179.22644326776125,
        "TrendFilterMA": 183.24864318847656,
        "SignalUnfiltered": "hold",
        "SignalFiltered": "hold"
    },
    {
        "Date": "2023-09-18T00:00:00",
        "Open": 175.1959303652364,
        "High": 178.0748391046168,
        "Low": 174.88818834345716,
        "Close": 176.6750946044922,
        "Volume": 67257600,
        "ShortEMA": 177.21146317415133,
        "LongEMA": 179.03745447788947,
        "TrendFilterMA": 183.0013980102539,
        "SignalUnfiltered": "hold",
        "SignalFiltered": "hold"
    },
    {
        "Date": "2023-09-19T00:00:00",
        "Open": 176.22837977645918,
        "High": 178.32302815377042,
        "Low": 175.84121799808253,
        "Close": 177.76710510253906,
        "Volume": 51826900,
        "ShortEMA": 177.29694654774946,
        "LongEMA": 178.94335452415982,
        "TrendFilterMA": 182.8170361328125,
        "SignalUnfiltered": "hold",
        "SignalFiltered": "hold"
    },
    {
        "Date": "2023-09-20T00:00:00",
        "Open": 177.95570880879336,
        "High": 178.3925098170354,
        "Low": 174.1237933470795,
        "Close": 174.21315002441406,
        "Volume": 58436200,
        "ShortEMA": 176.82251631339017,
        "LongEMA": 178.59296900566014,
        "TrendFilterMA": 182.57210388183594,
        "SignalUnfiltered": "hold",
        "SignalFiltered": "hold"
    },
    {
        "Date": "2023-09-21T00:00:00",
        "Open": 173.27997365508898,
        "High": 175.0172406192522,
        "Low": 172.5949916855764,
        "Close": 172.6644744873047,
        "Volume": 63047900,
        "ShortEMA": 176.1828175709155,
        "LongEMA": 178.15382126355973,
        "TrendFilterMA": 182.26268920898437,
        "SignalUnfiltered": "hold",
        "SignalFiltered": "hold"
    },
    {
        "Date": "2023-09-22T00:00:00",
        "Open": 173.39911221131908,
        "High": 175.79158086544706,
        "Low": 172.7836281326413,
        "Close": 173.5182342529297,
        "Volume": 56725400,
        "ShortEMA": 175.77288167584075,
        "LongEMA": 177.8104444479575,
        "TrendFilterMA": 181.95508239746093,
        "SignalUnfiltered": "hold",
        "SignalFiltered": "hold"
    },
    {
        "Date": "2023-09-25T00:00:00",
        "Open": 172.93251742028295,
        "High": 175.6823671360894,
        "Low": 172.88287819083024,
        "Close": 174.79884338378906,
        "Volume": 46172700,
        "ShortEMA": 175.6230296309097,
        "LongEMA": 177.58736288764874,
        "TrendFilterMA": 181.6701138305664,
        "SignalUnfiltered": "hold",
        "SignalFiltered": "hold"
    },
    {
        "Date": "2023-09-26T00:00:00",
        "Open": 173.54803864674588,
        "High": 173.92526351342306,
        "Low": 170.4110267791137,
        "Close": 170.70884704589844,
        "Volume": 64588900,
        "ShortEMA": 174.86700154090798,
        "LongEMA": 177.07784319566724,
        "TrendFilterMA": 181.23791381835937,
        "SignalUnfiltered": "hold",
        "SignalFiltered": "hold"
    },
    {
        "Date": "2023-09-27T00:00:00",
        "Open": 171.36404026565756,
        "High": 171.7809825966186,
        "Low": 167.82002287860425,
        "Close": 169.18997192382812,
        "Volume": 66921800,
        "ShortEMA": 173.99361236904954,
        "LongEMA": 176.49355643479026,
        "TrendFilterMA": 180.78049194335938,
        "SignalUnfiltered": "hold",
        "SignalFiltered": "hold"
    },
    {
        "Date": "2023-09-28T00:00:00",
        "Open": 168.10787564587397,
        "High": 170.77830558378838,
        "Low": 166.4003891832915,
        "Close": 169.44805908203125,
        "Volume": 56294400,
        "ShortEMA": 173.29429647873903,
        "LongEMA": 175.9716677419933,
        "TrendFilterMA": 180.30106781005858,
        "SignalUnfiltered": "hold",
        "SignalFiltered": "hold"
    },
    {
        "Date": "2023-09-29T00:00:00",
        "Open": 170.76839850543928,
        "High": 171.81076180692196,
        "Low": 169.10061419351356,
        "Close": 169.96429443359375,
        "Volume": 51814200,
        "ShortEMA": 172.7819884717936,
        "LongEMA": 175.52667712655628,
        "TrendFilterMA": 179.8710287475586,
        "SignalUnfiltered": "hold",
        "SignalFiltered": "hold"
    },
    {
        "Date": "2023-10-02T00:00:00",
        "Open": 169.97421860938772,
        "High": 173.03181060107437,
        "Low": 169.6863201427267,
        "Close": 172.48580932617188,
        "Volume": 52164500,
        "ShortEMA": 172.73642244939026,
        "LongEMA": 175.30142765986113,
        "TrendFilterMA": 179.51501495361327,
        "SignalUnfiltered": "hold",
        "SignalFiltered": "hold"
    },
    {
        "Date": "2023-10-03T00:00:00",
        "Open": 171.0066338674304,
        "High": 172.36667607241205,
        "Low": 169.5771240058018,
        "Close": 171.14561462402344,
        "Volume": 49594600,
        "ShortEMA": 172.49168278394922,
        "LongEMA": 174.99358965720648,
        "TrendFilterMA": 179.11613708496094,
        "SignalUnfiltered": "hold",
        "SignalFiltered": "hold"
    },
    {
        "Date": "2023-10-04T00:00:00",
        "Open": 169.84513086786842,
        "High": 172.94243978106925,
        "Low": 169.7260088454331,
        "Close": 172.3964385986328,
        "Volume": 53020300,
        "ShortEMA": 172.4770298323621,
        "LongEMA": 174.80120809731213,
        "TrendFilterMA": 178.72502532958984,
        "SignalUnfiltered": "hold",
        "SignalFiltered": "hold"
    },
    {
        "Date": "2023-10-05T00:00:00",
        "Open": 172.52551359241795,
        "High": 174.17343922355133,
        "Low": 171.42358924241523,
        "Close": 173.6373748779297,
        "Volume": 48527900,
        "ShortEMA": 172.65554445475712,
        "LongEMA": 174.71499822920973,
        "TrendFilterMA": 178.3412841796875,
        "SignalUnfiltered": "hold",
        "SignalFiltered": "hold"
    },
    {
        "Date": "2023-10-06T00:00:00",
        "Open": 172.53545399514545,
        "High": 176.69497045530053,
        "Low": 171.91995474415313,
        "Close": 176.1986083984375,
        "Volume": 57224100,
        "ShortEMA": 173.20063121532334,
        "LongEMA": 174.82489527878215,
        "TrendFilterMA": 178.0341470336914,
        "SignalUnfiltered": "hold",
        "SignalFiltered": "hold"
    },
    {
        "Date": "2023-10-09T00:00:00",
        "Open": 175.52353680032698,
        "High": 177.74724412480685,
        "Low": 174.52089096334598,
        "Close": 177.68768310546875,
        "Volume": 42390800,
        "ShortEMA": 173.89094689073033,
        "LongEMA": 175.03695363631448,
        "TrendFilterMA": 177.70504028320312,
        "SignalUnfiltered": "hold",
        "SignalFiltered": "hold"
    },
    {
        "Date": "2023-10-10T00:00:00",
        "Open": 176.80415770883764,
        "High": 178.41236580749592,
        "Low": 176.6552400140717,
        "Close": 177.092041015625,
        "Volume": 43698000,
        "ShortEMA": 174.3834229099449,
        "LongEMA": 175.18918233107823,
        "TrendFilterMA": 177.351728515625,
        "SignalUnfiltered": "hold",
        "SignalFiltered": "hold"
    },
    {
        "Date": "2023-10-11T00:00:00",
        "Open": 176.90342620076967,
        "High": 178.54143000452555,
        "Low": 176.30780084757703,
        "Close": 178.49179077148438,
        "Volume": 47551100,
        "ShortEMA": 175.0154795040279,
        "LongEMA": 175.43381999333053,
        "TrendFilterMA": 177.04306701660155,
        "SignalUnfiltered": "hold",
        "SignalFiltered": "hold"
    },
    {
        "Date": "2023-10-12T00:00:00",
        "Open": 178.75985973412483,
        "High": 181.01333283445837,
        "Low": 177.73733983917697,
        "Close": 179.39520263671875,
        "Volume": 56743100,
        "ShortEMA": 175.6892830629034,
        "LongEMA": 175.72725574469263,
        "TrendFilterMA": 176.81255096435547,
        "SignalUnfiltered": "hold",
        "SignalFiltered": "hold"
    },
    {
        "Date": "2023-10-13T00:00:00",
        "Open": 180.09999903884182,
        "High": 180.60628286156256,
        "Low": 176.84386529966793,
        "Close": 177.5487060546875,
        "Volume": 51427100,
        "ShortEMA": 175.97534813856248,
        "LongEMA": 175.86217798987744,
        "TrendFilterMA": 176.57306274414063,
        "SignalUnfiltered": "buy",
        "SignalFiltered": "hold"
    },
    {
        "Date": "2023-10-16T00:00:00",
        "Open": 175.46397958471027,
        "High": 177.7770284883398,
        "Low": 175.22572035442593,
        "Close": 177.41964721679688,
        "Volume": 52517000,
        "ShortEMA": 176.19754799675238,
        "LongEMA": 175.97754608076036,
        "TrendFilterMA": 176.51301116943358,
        "SignalUnfiltered": "hold",
        "SignalFiltered": "hold"
    },
    {
        "Date": "2023-10-17T00:00:00",
        "Open": 175.36470667426025,
        "High": 177.12183257732815,
        "Low": 173.5281761730158,
        "Close": 175.86106872558594,
        "Volume": 57549400,
        "ShortEMA": 176.14578195503447,
        "LongEMA": 175.96891812852522,
        "TrendFilterMA": 176.48404693603516,
        "SignalUnfiltered": "hold",
        "SignalFiltered": "hold"
    },
    {
        "Date": "2023-10-18T00:00:00",
        "Open": 174.30248985254676,
        "High": 176.28793794498117,
        "Low": 173.83590833900334,
        "Close": 174.5605926513672,
        "Volume": 54764400,
        "ShortEMA": 175.9019066775472,
        "LongEMA": 175.8645977228098,
        "TrendFilterMA": 176.41023742675782,
        "SignalUnfiltered": "hold",
        "SignalFiltered": "hold"
    },
    {
        "Date": "2023-10-19T00:00:00",
        "Open": 174.75913147519677,
        "High": 176.5460377577175,
        "Low": 173.9153251388443,
        "Close": 174.18336486816406,
        "Volume": 59302900,
        "ShortEMA": 175.6375156299498,
        "LongEMA": 175.740061955799,
        "TrendFilterMA": 176.3608056640625,
        "SignalUnfiltered": "sell",
        "SignalFiltered": "sell"
    },
    {
        "Date": "2023-10-20T00:00:00",
        "Open": 174.03445888939677,
        "High": 174.14365914589465,
        "Low": 171.38388737014972,
        "Close": 171.6221466064453,
        "Volume": 64189300,
        "ShortEMA": 175.01976654941066,
        "LongEMA": 175.43503118918022,
        "TrendFilterMA": 176.2645120239258,
        "SignalUnfiltered": "hold",
        "SignalFiltered": "hold"
    },
    {
        "Date": "2023-10-23T00:00:00",
        "Open": 169.66646713238327,
        "High": 172.7439025281915,
        "Low": 168.69358667928853,
        "Close": 171.7412567138672,
        "Volume": 55980100,
        "ShortEMA": 174.5153804208655,
        "LongEMA": 175.16141826508297,
        "TrendFilterMA": 176.1694091796875,
        "SignalUnfiltered": "hold",
        "SignalFiltered": "hold"
    },
    {
        "Date": "2023-10-24T00:00:00",
        "Open": 171.7909082758531,
        "High": 172.4063923696406,
        "Low": 170.20254365913797,
        "Close": 172.17807006835938,
        "Volume": 43816600,
        "ShortEMA": 174.15579421278764,
        "LongEMA": 174.9404295097701,
        "TrendFilterMA": 176.04988525390624,
        "SignalUnfiltered": "hold",
        "SignalFiltered": "hold"
    },
    {
        "Date": "2023-10-25T00:00:00",
        "Open": 170.62942613878033,
        "High": 171.80083332633419,
        "Low": 169.4083645680371,
        "Close": 169.8551025390625,
        "Volume": 57157000,
        "ShortEMA": 173.49414933990684,
        "LongEMA": 174.56373862305102,
        "TrendFilterMA": 175.92380981445314,
        "SignalUnfiltered": "hold",
        "SignalFiltered": "hold"
    },
    {
        "Date": "2023-10-26T00:00:00",
        "Open": 169.13038017633548,
        "High": 170.13304109397222,
        "Low": 164.46458048468762,
        "Close": 165.6757049560547,
        "Volume": 70625300,
        "ShortEMA": 172.29131174239112,
        "LongEMA": 173.90536575882908,
        "TrendFilterMA": 175.73161773681642,
        "SignalUnfiltered": "hold",
        "SignalFiltered": "hold"
    },
    {
        "Date": "2023-10-27T00:00:00",
        "Open": 165.69558183671225,
        "High": 167.73066925493364,
        "Low": 165.6161620916175,
        "Close": 166.9960479736328,
        "Volume": 58499100,
        "ShortEMA": 171.47665577796676,
        "LongEMA": 173.39356444140714,
        "TrendFilterMA": 175.61685913085938,
        "SignalUnfiltered": "hold",
        "SignalFiltered": "hold"
    },
    {
        "Date": "2023-10-30T00:00:00",
        "Open": 167.7902309189435,
        "High": 169.92458166587582,
        "Low": 167.64131321590813,
        "Close": 169.0509796142578,
        "Volume": 51131000,
        "ShortEMA": 171.10347482970383,
        "LongEMA": 173.07189149124792,
        "TrendFilterMA": 175.5334701538086,
        "SignalUnfiltered": "hold",
        "SignalFiltered": "hold"
    },
    {
        "Date": "2023-10-31T00:00:00",
        "Open": 168.11782995408234,
        "High": 169.6565401685357,
        "Low": 166.67836791176023,
        "Close": 169.52749633789062,
        "Volume": 44846000,
        "ShortEMA": 170.86101660019412,
        "LongEMA": 172.80934370211034,
        "TrendFilterMA": 175.43280822753906,
        "SignalUnfiltered": "hold",
        "SignalFiltered": "hold"
    },
    {
        "Date": "2023-11-01T00:00:00",
        "Open": 169.75581666227828,
        "High": 172.9623111800798,
        "Low": 168.88221462983017,
        "Close": 172.70420837402344,
        "Volume": 56934900,
        "ShortEMA": 171.14458456539862,
        "LongEMA": 172.80155590002983,
        "TrendFilterMA": 175.3680825805664,
        "SignalUnfiltered": "hold",
        "SignalFiltered": "hold"
    },
    {
        "Date": "2023-11-02T00:00:00",
        "Open": 174.2429429068373,
        "High": 176.4864939793014,
        "Low": 174.18338188289627,
        "Close": 176.2780303955078,
        "Volume": 77334800,
        "ShortEMA": 171.93434546233848,
        "LongEMA": 173.05907252932448,
        "TrendFilterMA": 175.29759979248047,
        "SignalUnfiltered": "hold",
        "SignalFiltered": "hold"
    },
    {
        "Date": "2023-11-03T00:00:00",
        "Open": 172.97224682902157,
        "High": 175.53347673875106,
        "Low": 172.08872301559984,
        "Close": 175.3647003173828,
        "Volume": 79763700,
        "ShortEMA": 172.46209236311452,
        "LongEMA": 173.22985977288437,
        "TrendFilterMA": 175.30296020507814,
        "SignalUnfiltered": "hold",
        "SignalFiltered": "hold"
    },
    {
        "Date": "2023-11-06T00:00:00",
        "Open": 175.09669429529205,
        "High": 178.12449090151532,
        "Low": 174.92793300379333,
        "Close": 177.9259490966797,
        "Volume": 63841300,
        "ShortEMA": 173.30268570673994,
        "LongEMA": 173.57771824131365,
        "TrendFilterMA": 175.3152700805664,
        "SignalUnfiltered": "hold",
        "SignalFiltered": "hold"
    },
    {
        "Date": "2023-11-07T00:00:00",
        "Open": 177.87630973489087,
        "High": 181.1126002277605,
        "Low": 177.66784614167742,
        "Close": 180.4971160888672,
        "Volume": 70530000,
        "ShortEMA": 174.40952115014414,
        "LongEMA": 174.0902662300213,
        "TrendFilterMA": 175.34763305664063,
        "SignalUnfiltered": "buy",
        "SignalFiltered": "hold"
    },
    {
        "Date": "2023-11-08T00:00:00",
        "Open": 181.02323134779837,
        "High": 182.1152186825965,
        "Low": 180.26875139702054,
        "Close": 181.55929565429688,
        "Volume": 49340300,
        "ShortEMA": 175.50948645847532,
        "LongEMA": 174.64352766885654,
        "TrendFilterMA": 175.32321197509765,
        "SignalUnfiltered": "hold",
        "SignalFiltered": "hold"
    },
    {
        "Date": "2023-11-09T00:00:00",
        "Open": 181.62879543623518,
        "High": 182.78034380026955,
        "Low": 180.48715371155149,
        "Close": 181.08279418945312,
        "Volume": 53763500,
        "ShortEMA": 176.3669184170873,
        "LongEMA": 175.1205103740859,
        "TrendFilterMA": 175.21917449951172,
        "SignalUnfiltered": "hold",
        "SignalFiltered": "hold"
    },
    {
        "Date": "2023-11-10T00:00:00",
        "Open": 182.87206148972973,
        "High": 185.4565506612299,
        "Low": 182.43468499907056,
        "Close": 185.2875518798828,
        "Volume": 66133400,
        "ShortEMA": 177.7393235652097,
        "LongEMA": 175.8736245597005,
        "TrendFilterMA": 175.1948648071289,
        "SignalUnfiltered": "hold",
        "SignalFiltered": "hold"
    },
    {
        "Date": "2023-11-13T00:00:00",
        "Open": 184.71099921820172,
        "High": 184.9197374055116,
        "Low": 183.11060738869827,
        "Close": 183.69708251953125,
        "Volume": 43627500,
        "ShortEMA": 178.65590186587454,
        "LongEMA": 176.4531399641324,
        "TrendFilterMA": 175.10717651367187,
        "SignalUnfiltered": "hold",
        "SignalFiltered": "hold"
    },
    {
        "Date": "2023-11-14T00:00:00",
        "Open": 186.57980822279126,
        "High": 186.98736499365313,
        "Low": 185.18816945365924,
        "Close": 186.3213653564453,
        "Volume": 60108400,
        "ShortEMA": 179.83520394134698,
        "LongEMA": 177.18411962282224,
        "TrendFilterMA": 175.0672085571289,
        "SignalUnfiltered": "hold",
        "SignalFiltered": "hold"
    },
    {
        "Date": "2023-11-15T00:00:00",
        "Open": 186.72890587030213,
        "High": 188.36905250310778,
        "Low": 186.65931635404164,
        "Close": 186.887939453125,
        "Volume": 53790500,
        "ShortEMA": 180.92024017392822,
        "LongEMA": 177.90292109173356,
        "TrendFilterMA": 175.1733837890625,
        "SignalUnfiltered": "hold",
        "SignalFiltered": "hold"
    },
    {
        "Date": "2023-11-16T00:00:00",
        "Open": 188.43864070160558,
        "High": 189.82034448090351,
        "Low": 187.52411797622008,
        "Close": 188.5778045654297,
        "Volume": 54412900,
        "ShortEMA": 182.09832700338998,
        "LongEMA": 178.69365320089625,
        "TrendFilterMA": 175.41957824707032,
        "SignalUnfiltered": "hold",
        "SignalFiltered": "hold"
    },
    {
        "Date": "2023-11-17T00:00:00",
        "Open": 189.11457782649978,
        "High": 189.24380683321974,
        "Low": 187.44461143684416,
        "Close": 188.55792236328125,
        "Volume": 50922700,
        "ShortEMA": 183.09211090491172,
        "LongEMA": 179.42433980551735,
        "TrendFilterMA": 175.65306518554686,
        "SignalUnfiltered": "hold",
        "SignalFiltered": "hold"
    },
    {
        "Date": "2023-11-20T00:00:00",
        "Open": 188.75671623264228,
        "High": 190.76466491067268,
        "Low": 188.7467813740569,
        "Close": 190.30740356445312,
        "Volume": 46505100,
        "ShortEMA": 184.20215592945655,
        "LongEMA": 180.23049267654963,
        "TrendFilterMA": 175.89811370849608,
        "SignalUnfiltered": "hold",
        "SignalFiltered": "hold"
    },
    {
        "Date": "2023-11-21T00:00:00",
        "Open": 190.2676365405526,
        "High": 190.37698064874536,
        "Low": 188.60760520178732,
        "Close": 189.50222778320312,
        "Volume": 38134500,
        "ShortEMA": 185.01755159926373,
        "LongEMA": 180.91728786963506,
        "TrendFilterMA": 176.18781311035156,
        "SignalUnfiltered": "hold",
        "SignalFiltered": "hold"
    },
    {
        "Date": "2023-11-22T00:00:00",
        "Open": 190.34717704028523,
        "High": 191.77857025832532,
        "Low": 189.6911123355231,
        "Close": 190.16824340820312,
        "Volume": 39617700,
        "ShortEMA": 185.80996572371595,
        "LongEMA": 181.60254383545492,
        "TrendFilterMA": 176.53232849121093,
        "SignalUnfiltered": "hold",
        "SignalFiltered": "hold"
    },
    {
        "Date": "2023-11-24T00:00:00",
        "Open": 189.73086532541635,
        "High": 189.76068506922263,
        "Low": 188.1205384889839,
        "Close": 188.83624267578125,
        "Volume": 24048300,
        "ShortEMA": 186.27554679326445,
        "LongEMA": 182.1383733791828,
        "TrendFilterMA": 176.81982666015625,
        "SignalUnfiltered": "hold",
        "SignalFiltered": "hold"
    },
    {
        "Date": "2023-11-27T00:00:00",
        "Open": 188.78654712309,
        "High": 189.53207108953595,
        "Low": 187.77263028176083,
        "Close": 188.65731811523438,
        "Volume": 40552600,
        "ShortEMA": 186.6419731504906,
        "LongEMA": 182.6212581744459,
        "TrendFilterMA": 177.1182403564453,
        "SignalUnfiltered": "hold",
        "SignalFiltered": "hold"
    },
    {
        "Date": "2023-11-28T00:00:00",
        "Open": 188.64737693705334,
        "High": 189.9396214691522,
        "Low": 188.26963995303524,
        "Close": 189.263671875,
        "Volume": 38415400,
        "ShortEMA": 187.04531141579974,
        "LongEMA": 183.11328881893138,
        "TrendFilterMA": 177.37001190185546,
        "SignalUnfiltered": "hold",
        "SignalFiltered": "hold"
    },
    {
        "Date": "2023-11-29T00:00:00",
        "Open": 189.7607054145589,
        "High": 190.9436059381113,
        "Low": 187.84223090795535,
        "Close": 188.23983764648438,
        "Volume": 43014200,
        "ShortEMA": 187.22908468205893,
        "LongEMA": 183.4930331765279,
        "TrendFilterMA": 177.57946655273437,
        "SignalUnfiltered": "hold",
        "SignalFiltered": "hold"
    },
    {
        "Date": "2023-11-30T00:00:00",
        "Open": 188.70701635554832,
        "High": 189.1841625986753,
        "Low": 187.06686975200412,
        "Close": 188.8163604736328,
        "Volume": 48794400,
        "ShortEMA": 187.4732809576857,
        "LongEMA": 183.88735371705417,
        "TrendFilterMA": 177.87153076171876,
        "SignalUnfiltered": "hold",
        "SignalFiltered": "hold"
    },
    {
        "Date": "2023-12-01T00:00:00",
        "Open": 189.19409067360718,
        "High": 190.41674564636727,
        "Low": 188.10064953196948,
        "Close": 190.09866333007812,
        "Volume": 45679300,
        "ShortEMA": 187.87718593805377,
        "LongEMA": 184.3474507254263,
        "TrendFilterMA": 178.22021453857423,
        "SignalUnfiltered": "hold",
        "SignalFiltered": "hold"
    },
    {
        "Date": "2023-12-04T00:00:00",
        "Open": 188.84617430866663,
        "High": 188.91576382150808,
        "Low": 186.33127483914026,
        "Close": 188.29945373535156,
        "Volume": 43389500,
        "ShortEMA": 187.9421502145611,
        "LongEMA": 184.6401916891245,
        "TrendFilterMA": 178.51583892822265,
        "SignalUnfiltered": "hold",
        "SignalFiltered": "hold"
    },
    {
        "Date": "2023-12-05T00:00:00",
        "Open": 189.07482149235318,
        "High": 193.23980256929687,
        "Low": 189.0449865799245,
        "Close": 192.26565551757812,
        "Volume": 66628400,
        "ShortEMA": 188.60730487656372,
        "LongEMA": 185.20504086160253,
        "TrendFilterMA": 178.86517517089842,
        "SignalUnfiltered": "hold",
        "SignalFiltered": "hold"
    },
    {
        "Date": "2023-12-06T00:00:00",
        "Open": 193.28950362567244,
        "High": 193.5976510937421,
        "Low": 190.9634725753497,
        "Close": 191.17222595214844,
        "Volume": 41089700,
        "ShortEMA": 189.00190811896135,
        "LongEMA": 185.64705457201333,
        "TrendFilterMA": 179.27444274902345,
        "SignalUnfiltered": "hold",
        "SignalFiltered": "hold"
    },
    {
        "Date": "2023-12-07T00:00:00",
        "Open": 192.4744006383907,
        "High": 193.8362194805571,
        "Low": 192.43463086867496,
        "Close": 193.11058044433594,
        "Volume": 47477700,
        "ShortEMA": 189.63401155363437,
        "LongEMA": 186.19990834033354,
        "TrendFilterMA": 179.7528549194336,
        "SignalUnfiltered": "hold",
        "SignalFiltered": "hold"
    },
    {
        "Date": "2023-12-08T00:00:00",
        "Open": 193.04099429291227,
        "High": 194.8203199094653,
        "Low": 192.5141585929263,
        "Close": 194.5419921875,
        "Volume": 53377300,
        "ShortEMA": 190.389085497306,
        "LongEMA": 186.81784047716067,
        "TrendFilterMA": 180.25473358154298,
        "SignalUnfiltered": "hold",
        "SignalFiltered": "hold"
    },
    {
        "Date": "2023-12-11T00:00:00",
        "Open": 191.9575100014726,
        "High": 192.33524699521988,
        "Low": 190.27759358324766,
        "Close": 192.02708435058594,
        "Volume": 60943700,
        "ShortEMA": 190.64108532088756,
        "LongEMA": 187.20371039371068,
        "TrendFilterMA": 180.6959893798828,
        "SignalUnfiltered": "hold",
        "SignalFiltered": "hold"
    },
    {
        "Date": "2023-12-12T00:00:00",
        "Open": 191.92769665062553,
        "High": 193.5579084922386,
        "Low": 190.5758125501861,
        "Close": 193.5479736328125,
        "Volume": 52696900,
        "ShortEMA": 191.08829890733753,
        "LongEMA": 187.67365581882933,
        "TrendFilterMA": 181.11723266601564,
        "SignalUnfiltered": "hold",
        "SignalFiltered": "hold"
    },
    {
        "Date": "2023-12-13T00:00:00",
        "Open": 193.925682544677,
        "High": 196.8183190559037,
        "Low": 193.68712459255818,
        "Close": 196.778564453125,
        "Volume": 70404200,
        "ShortEMA": 191.9637243759202,
        "LongEMA": 188.34809349544383,
        "TrendFilterMA": 181.62989166259766,
        "SignalUnfiltered": "hold",
        "SignalFiltered": "hold"
    },
    {
        "Date": "2023-12-14T00:00:00",
        "Open": 196.83819885132337,
        "High": 198.42864077264184,
        "Low": 194.98929893159502,
        "Close": 196.9276580810547,
        "Volume": 66831600,
        "ShortEMA": 192.72740648440242,
        "LongEMA": 188.98361679808167,
        "TrendFilterMA": 182.1205160522461,
        "SignalUnfiltered": "hold",
        "SignalFiltered": "hold"
    },
    {
        "Date": "2023-12-15T00:00:00",
        "Open": 196.35111463057538,
        "High": 197.21591750628332,
        "Low": 195.82427895138287,
        "Close": 196.39088439941406,
        "Volume": 128256700,
        "ShortEMA": 193.29101847132728,
        "LongEMA": 189.53230328706925,
        "TrendFilterMA": 182.57558624267577,
        "SignalUnfiltered": "hold",
        "SignalFiltered": "hold"
    },
    {
        "Date": "2023-12-18T00:00:00",
        "Open": 194.9197048287757,
        "High": 195.45649052996882,
        "Low": 193.2298536912898,
        "Close": 194.7209014892578,
        "Volume": 55751900,
        "ShortEMA": 193.51100047408582,
        "LongEMA": 189.91664389463878,
        "TrendFilterMA": 182.9460321044922,
        "SignalUnfiltered": "hold",
        "SignalFiltered": "hold"
    },
    {
        "Date": "2023-12-19T00:00:00",
        "Open": 194.98931995291727,
        "High": 195.77459855586707,
        "Low": 194.72092706706565,
        "Close": 195.76466369628906,
        "Volume": 40714100,
        "ShortEMA": 193.8577178928863,
        "LongEMA": 190.34983054661288,
        "TrendFilterMA": 183.3075717163086,
        "SignalUnfiltered": "hold",
        "SignalFiltered": "hold"
    },
    {
        "Date": "2023-12-20T00:00:00",
        "Open": 195.72488988877126,
        "High": 196.50023361616374,
        "Low": 193.66725158691406,
        "Close": 193.66725158691406,
        "Volume": 52242800,
        "ShortEMA": 193.8284153842752,
        "LongEMA": 190.59556543848703,
        "TrendFilterMA": 183.63907592773438,
        "SignalUnfiltered": "hold",
        "SignalFiltered": "hold"
    },
    {
        "Date": "2023-12-21T00:00:00",
        "Open": 194.9296507492267,
        "High": 195.90379770975298,
        "Low": 192.34516188676014,
        "Close": 193.5181121826172,
        "Volume": 46482500,
        "ShortEMA": 193.78067643017397,
        "LongEMA": 190.81205038249666,
        "TrendFilterMA": 183.93960235595702,
        "SignalUnfiltered": "hold",
        "SignalFiltered": "hold"
    },
    {
        "Date": "2023-12-22T00:00:00",
        "Open": 194.01515250091973,
        "High": 194.24379077463595,
        "Low": 191.8183503425399,
        "Close": 192.44459533691406,
        "Volume": 37122800,
        "ShortEMA": 193.57512549274938,
        "LongEMA": 190.93297963837944,
        "TrendFilterMA": 184.20059020996095,
        "SignalUnfiltered": "hold",
        "SignalFiltered": "hold"
    },
    {
        "Date": "2023-12-26T00:00:00",
        "Open": 192.45452839560733,
        "High": 192.73285613100865,
        "Low": 191.67918468017166,
        "Close": 191.8978729248047,
        "Volume": 28919300,
        "ShortEMA": 193.3170866361425,
        "LongEMA": 191.00445321515167,
        "TrendFilterMA": 184.48757354736327,
        "SignalUnfiltered": "hold",
        "SignalFiltered": "hold"
    },
    {
        "Date": "2023-12-27T00:00:00",
        "Open": 191.34121910492223,
        "High": 192.34518593287333,
        "Low": 189.94956524818429,
        "Close": 191.9972686767578,
        "Volume": 48087700,
        "ShortEMA": 193.1140377193141,
        "LongEMA": 191.07799510119656,
        "TrendFilterMA": 184.7791259765625,
        "SignalUnfiltered": "hold",
        "SignalFiltered": "hold"
    },
    {
        "Date": "2023-12-28T00:00:00",
        "Open": 192.98136861854135,
        "High": 193.4982694967864,
        "Low": 192.01715638138543,
        "Close": 192.42471313476562,
        "Volume": 34049900,
        "ShortEMA": 193.0079877832297,
        "LongEMA": 191.17775199257204,
        "TrendFilterMA": 185.1103988647461,
        "SignalUnfiltered": "hold",
        "SignalFiltered": "hold"
    },
    {
        "Date": "2023-12-29T00:00:00",
        "Open": 192.7427850763616,
        "High": 193.23980104114617,
        "Low": 190.58573760932344,
        "Close": 191.38096618652344,
        "Volume": 42628800,
        "ShortEMA": 192.7576767683518,
        "LongEMA": 191.1928048958277,
        "TrendFilterMA": 185.44680633544922,
        "SignalUnfiltered": "hold",
        "SignalFiltered": "hold"
    }
]